qtilities/__init__.py
qtilities/pqp/__init__.py
qtilities/pqp/client.py
qtilities/pqp/previewer.py
qtilities/pyqmlscene/__init__.py
qtilities/pyqmlscene/main.py
qtilities/qmltags/__init__.py
qtilities/qmltags/main.py
qtilities-0.8.dist-info/DESCRIPTION.rst
qtilities-0.8.dist-info/METADATA
qtilities-0.8.dist-info/RECORD
qtilities-0.8.dist-info/WHEEL
qtilities-0.8.dist-info/entry_points.txt
qtilities-0.8.dist-info/metadata.json
qtilities-0.8.dist-info/top_level.txt
