Metadata-Version: 2.0
Name: qtilities
Version: 0.8
Summary: Utilities for PyQt5 development
Home-page: https://github.com/pylipp/qtilities
Author: Philipp Metzner
Author-email: beth.aleph@yahoo.de
License: GPLv3
Platform: UNKNOWN
Requires-Dist: PyQt5
